macrel/AMP_features.py
macrel/AMP_predict.py
macrel/ORFs_prediction.py
macrel/__init__.py
macrel/ampsphere.py
macrel/database.py
macrel/fasta.py
macrel/filter_smorfs.py
macrel/macrel_features.py
macrel/macrel_version.py
macrel/main.py
macrel/output.py
macrel/utils.py
macrel/data/models/AMP.pkl.gz
macrel/data/models/Hemo.pkl.gz
macrel/data/scripts/count.ngl
macrel/data/scripts/trim.pe.ngl
macrel/data/scripts/trim.se.ngl
macrel/tests/__init__.py
macrel/tests/test_ampsphere.py
macrel/tests/test_features.py
macrel/tests/test_predict.py
macrel-1.5.0.dist-info/LICENSE
macrel-1.5.0.dist-info/METADATA
macrel-1.5.0.dist-info/WHEEL
macrel-1.5.0.dist-info/entry_points.txt
macrel-1.5.0.dist-info/top_level.txt
macrel-1.5.0.dist-info/RECORD
